streamlit_when2meet/__init__.py
streamlit_when2meet/example.py
streamlit_when2meet/frontend/build/asset-manifest.json
streamlit_when2meet/frontend/build/bootstrap.min.css
streamlit_when2meet/frontend/build/index.html
streamlit_when2meet/frontend/build/static/js/main.c64cc9f8.js
streamlit_when2meet/frontend/build/static/js/main.c64cc9f8.js.LICENSE.txt
streamlit_when2meet/frontend/build/static/js/main.c64cc9f8.js.map
streamlit_when2meet-0.0.5.dist-info/LICENSE
streamlit_when2meet-0.0.5.dist-info/METADATA
streamlit_when2meet-0.0.5.dist-info/WHEEL
streamlit_when2meet-0.0.5.dist-info/top_level.txt
streamlit_when2meet-0.0.5.dist-info/RECORD
